turta_relayhat/Turta_RelayHAT.py
turta_relayhat/__init__.py
turta_relayhat-1.1.2.dist-info/LICENCE
turta_relayhat-1.1.2.dist-info/METADATA
turta_relayhat-1.1.2.dist-info/WHEEL
turta_relayhat-1.1.2.dist-info/top_level.txt
turta_relayhat-1.1.2.dist-info/RECORD
